mojo/__init__.py
mojo/apps/account/__init__.py
mojo/apps/account/admin.py
mojo/apps/account/apps.py
mojo/apps/account/management/__init__.py
mojo/apps/account/management/commands/__init__.py
mojo/apps/account/management/commands/model_permissions.py
mojo/apps/account/management/commands/serializer_admin.py
mojo/apps/account/management/commands/status.py
mojo/apps/account/migrations/0001_initial.py
mojo/apps/account/migrations/0002_user_is_email_verified_user_is_phone_verified.py
mojo/apps/account/migrations/0003_group_mojo_secrets_user_mojo_secrets.py
mojo/apps/account/migrations/0004_user_avatar.py
mojo/apps/account/migrations/0005_group_last_activity.py
mojo/apps/account/migrations/0006_add_device_tracking_models.py
mojo/apps/account/migrations/0007_delete_userdevicelocation.py
mojo/apps/account/migrations/0008_userdevicelocation.py
mojo/apps/account/migrations/0009_geolocatedip_subnet.py
mojo/apps/account/migrations/0010_group_avatar.py
mojo/apps/account/migrations/0011_user_org_registereddevice_pushconfig_and_more.py
mojo/apps/account/migrations/0012_remove_pushconfig_apns_key_file_and_more.py
mojo/apps/account/migrations/0013_pushconfig_test_mode_alter_pushconfig_apns_enabled_and_more.py
mojo/apps/account/migrations/0014_notificationdelivery_data_payload_and_more.py
mojo/apps/account/migrations/0015_groupmember_last_activity.py
mojo/apps/account/migrations/0016_geolocatedip_asn_geolocatedip_asn_org_and_more.py
mojo/apps/account/migrations/0017_geolocatedip_last_seen.py
mojo/apps/account/migrations/0018_geolocatedip_is_known_abuser_and_more.py
mojo/apps/account/migrations/0019_alter_userdevicelocation_user.py
mojo/apps/account/migrations/0020_remove_pushconfig_apns_bundle_id_and_more.py
mojo/apps/account/migrations/0021_remove_pushconfig_fcm_sender_id.py
mojo/apps/account/migrations/0022_geolocatedip_is_mobile_mobile_carrier.py
mojo/apps/account/migrations/0023_rename_account_geo_is_mobi_8a7c2e_idx_account_geo_is_mobi_06bfa8_idx_and_more.py
django_nativemojo-1.0.10.dist-info/METADATA
django_nativemojo-1.0.10.dist-info/WHEEL
django_nativemojo-1.0.10.dist-info/licenses/LICENSE
django_nativemojo-1.0.10.dist-info/licenses/NOTICE
django_nativemojo-1.0.10.dist-info/RECORD
