Metadata-Version: 2.4
Name: django-nativemojo
Version: 1.0.10
Summary: A REST framework for DJANGO with some extra apps that make it easy to provide a secure robust graph like REST API.
License-Expression: MIT
License-File: LICENSE
License-File: NOTICE
Author: MOJO Dev Team
Author-email: gotmojo@nativemojo.com
Requires-Python: >=3.10,<4.0
Classifier: Programming Language :: Python :: 3
Classifier: Programming Language :: Python :: 3.10
Classifier: Programming Language :: Python :: 3.11
Classifier: Programming Language :: Python :: 3.12
Classifier: Programming Language :: Python :: 3.13
Classifier: Programming Language :: Python :: 3.14
Requires-Dist: Pillow (>=10.4.0,<11.0.0)
Requires-Dist: django (>=4.2.18,<6.0.0)
Requires-Dist: faker (>=35.2.0,<36.0.0)
Requires-Dist: gevent (>=25.5.1,<26.0.0)
Requires-Dist: mistune (>=3.0.2,<4.0.0)
Requires-Dist: phonenumberslite (>=9.0.17,<10.0.0)
Requires-Dist: pycryptodome (>=3.21.0,<4.0.0)
Requires-Dist: pygments (>=2.18.0,<3.0.0)
Requires-Dist: pyjwt (>=2.10.1,<3.0.0)
Requires-Dist: pyobjict (>=2.0.2,<4.0.0)
Requires-Dist: python-magic (>=0.4.27,<0.5.0)
Requires-Dist: pytz (>=2025.1,<2026.0)
Requires-Dist: qrcode[pil] (>=7.4.2,<8.0.0)
Requires-Dist: redis (>=3.5.3,<6.0.0)
Requires-Dist: requests (>=2.32.3,<3.0.0)
Requires-Dist: twilio (>=9.8.4,<10.0.0)
Requires-Dist: ua-parser (>=1.0.1,<2.0.0)
Requires-Dist: ujson (>=5.10.0,<6.0.0)
